jackals/__init__.py
jackals/dataframe.py
jackals/series.py
jackals-0.1.4.dist-info/LICENSE
jackals-0.1.4.dist-info/METADATA
jackals-0.1.4.dist-info/WHEEL
jackals-0.1.4.dist-info/top_level.txt
jackals-0.1.4.dist-info/RECORD
