Metadata-Version: 2.1
Name: jackals
Version: 0.1.4
Summary: A small example package
Author: Pietro Bonazzi
Author-email: Pietro Bonazzi <pebonazzi@gmail.com>
License: MIT
Project-URL: Homepage, https://github.com/pypa/sampleproject
Project-URL: Bug Tracker, https://github.com/pypa/sampleproject/issues
Classifier: Programming Language :: Python :: 3
Classifier: License :: OSI Approved :: MIT License
Classifier: Operating System :: OS Independent
Requires-Python: >=3.7
License-File: LICENSE
